doppler_injector/__init__.py
doppler_injector/main.py
doppler_injector-0.1.0.dist-info/METADATA
doppler_injector-0.1.0.dist-info/WHEEL
doppler_injector-0.1.0.dist-info/RECORD
