Metadata-Version: 2.1
Name: doppler-injector
Version: 0.1.0
Summary: 
Author: Evan Baird
Author-email: evanbaird@evans-mbp.lan
Requires-Python: >=3.11,<4.0
Classifier: Programming Language :: Python :: 3
Classifier: Programming Language :: Python :: 3.11
Classifier: Programming Language :: Python :: 3.12
Requires-Dist: doppler-env (>=0.3.1,<0.4.0)
Requires-Dist: python-box (>=7.1.1,<8.0.0)
